LAMDA_SSL/__init__.py
LAMDA_SSL/utils.py
LAMDA_SSL/Algorithm/__init__.py
LAMDA_SSL/Algorithm/Classification/Assemble.py
LAMDA_SSL/Algorithm/Classification/Co_Training.py
LAMDA_SSL/Algorithm/Classification/FixMatch.py
LAMDA_SSL/Algorithm/Classification/FlexMatch.py
LAMDA_SSL/Algorithm/Classification/GAT.py
LAMDA_SSL/Algorithm/Classification/GCN.py
LAMDA_SSL/Algorithm/Classification/ICT.py
LAMDA_SSL/Algorithm/Classification/ImprovedGAN.py
LAMDA_SSL/Algorithm/Classification/LabelPropagation.py
LAMDA_SSL/Algorithm/Classification/LabelSpreading.py
LAMDA_SSL/Algorithm/Classification/LadderNetwork.py
LAMDA_SSL/Algorithm/Classification/LapSVM.py
LAMDA_SSL/Algorithm/Classification/MeanTeacher.py
LAMDA_SSL/Algorithm/Classification/MixMatch.py
LAMDA_SSL/Algorithm/Classification/PiModel.py
LAMDA_SSL/Algorithm/Classification/PseudoLabel.py
LAMDA_SSL/Algorithm/Classification/ReMixMatch.py
LAMDA_SSL/Algorithm/Classification/S4L.py
LAMDA_SSL/Algorithm/Classification/SDNE.py
LAMDA_SSL/Algorithm/Classification/SSGMM.py
LAMDA_SSL/Algorithm/Classification/SSVAE.py
LAMDA_SSL/Algorithm/Classification/SemiBoost.py
LAMDA_SSL/Algorithm/Classification/TSVM.py
LAMDA_SSL/Algorithm/Classification/TemporalEnsembling.py
LAMDA_SSL/Algorithm/Classification/Tri_Training.py
LAMDA_SSL/Algorithm/Classification/UDA.py
LAMDA_SSL/Algorithm/Classification/VAT.py
LAMDA_SSL/Algorithm/Classification/__init__.py
LAMDA_SSL/Algorithm/Clustering/Constrained_Seed_k_means.py
LAMDA_SSL/Algorithm/Clustering/Constrained_k_means.py
LAMDA_SSL/Algorithm/Clustering/__init__.py
LAMDA_SSL/Algorithm/Regression/CoReg.py
LAMDA_SSL/Algorithm/Regression/ICTReg.py
LAMDA_SSL/Algorithm/Regression/MeanTeacherReg.py
LAMDA_SSL/Algorithm/Regression/PiModelReg.py
LAMDA_SSL/Algorithm/Regression/__init__.py
LAMDA_SSL/Augmentation/__init__.py
LAMDA_SSL/Augmentation/Graph/DropEdges.py
LAMDA_SSL/Augmentation/Graph/DropNodes.py
LAMDA_SSL/Augmentation/Graph/__init__.py
LAMDA_SSL/Augmentation/Tabular/Noise.py
LAMDA_SSL-1.0.2.dist-info/LICENSE
LAMDA_SSL-1.0.2.dist-info/METADATA
LAMDA_SSL-1.0.2.dist-info/WHEEL
LAMDA_SSL-1.0.2.dist-info/top_level.txt
LAMDA_SSL-1.0.2.dist-info/RECORD
