Metadata-Version: 2.1
Name: LAMDA-SSL
Version: 1.0.2
Summary: LAMDA-SSL is an useful toolkit for semi-supervised learning.
Home-page: https://github.com/YGZWQZD/LAMDA-SSL
Author: Lin-Han Jia, Lan-Zhe Guo, Zhi Zhou, Yu-Feng Li
Author-email: 1129198222@qq.com
License: MIT
Keywords: Semi-Supervised Learning,Machine Learning,Deep Learning,Toolkit
Platform: UNKNOWN
Classifier: Programming Language :: Python :: 3
Classifier: License :: OSI Approved :: MIT License
Classifier: Operating System :: OS Independent
Requires-Python: >=3.7
License-File: LICENSE
Requires-Dist: scikit-learn
Requires-Dist: torchtext
Requires-Dist: torchvision
Requires-Dist: torch-geometric
Requires-Dist: Pillow
Requires-Dist: numpy
Requires-Dist: scipy
Requires-Dist: pandas
Requires-Dist: matplotlib
